osio_api_tests-1.0.2.dev1.data/data/scripts/run_me.sh
osio_api_tests-1.0.2.dev1.data/scripts/run_me.sh
osio_api_tests-1.0.2.dev1.dist-info/DESCRIPTION.rst
osio_api_tests-1.0.2.dev1.dist-info/METADATA
osio_api_tests-1.0.2.dev1.dist-info/RECORD
osio_api_tests-1.0.2.dev1.dist-info/WHEEL
osio_api_tests-1.0.2.dev1.dist-info/metadata.json
osio_api_tests-1.0.2.dev1.dist-info/top_level.txt
src/__init__.py
src/conftest.py
src/test_planner.py
src/support/__init__.py
src/support/constants.py
src/support/helpers.py
src/support/post_jsons/add_wi_comment.json
src/support/post_jsons/add_wi_label.json
src/support/post_jsons/add_wi_labels.json
src/support/post_jsons/create_child_area.json
src/support/post_jsons/create_child_iteration.json
src/support/post_jsons/create_label.json
src/support/post_jsons/create_space.json
src/support/post_jsons/create_wi_hierarchy.json
src/support/post_jsons/create_wi_in_backlog.json
src/support/post_jsons/create_wi_in_iter.json
src/support/post_jsons/enable_experimental.json
